{
  "@context": "https://schema.org",
  "@type": "WebPage",
  "name": "Industries We Serve — Unbox Robotics",
  "url": "https://unboxrobotics.com/industry",
  "description": "Unbox Robotics serves e-commerce, retail, 3PL, and CEP industries with AI-powered robotic sortation systems tailored to each sector's logistics needs.",
  "publisher": {
    "@type": "Organization",
    "name": "Unbox Robotics",
    "url": "https://unboxrobotics.com",
    "logo": "https://unboxrobotics.com/nav-logo.png",
    "sameAs": [
      "https://www.linkedin.com/company/unboxrobotics/",
      "https://x.com/RoboticsUnbox",
      "https://www.facebook.com/unboxrobotics/",
      "https://www.instagram.com/lifeatunbox/",
      "https://www.youtube.com/@unboxrobotics"
    ]
  }
}